multiplyByTwo/__init__.py
multiplyByTwo/multiplication.py
multiplyByTwo/multiplication_1.py
multiplyByTwo-0.1.0.dist-info/METADATA
multiplyByTwo-0.1.0.dist-info/WHEEL
multiplyByTwo-0.1.0.dist-info/top_level.txt
multiplyByTwo-0.1.0.dist-info/RECORD
